Workbook
Name Building: #REF!
Name Building: #REF!
Name Building: #REF!
Name Class: '[2]PPM Class'!$A$2:$A$4
Name CostCoentre: '[2]Cost Centres'!$B$4:$B$1000
Name Days: [2]Months!$B$1:$B$7
Name Location: #REF!
Name Location: #REF!
Name Location: #REF!
Name Location2: #REF!
Name Location2: #REF!
Name Location2: #REF!
Name Locations: #REF!
Name Locations: #REF!
Name Locations: #REF!
Name PPMFreq: '[2]PPM Frequency'!$A$2:$A$4
Name PPMIns: #REF!
Name PPMIns: #REF!
Name PPMIns: #REF!
Name PPMUnits: '[2]PPM Units'!$A$2:$A$53
Name Search: '[3]Full Asset'!$E$2:$F$8028
Name System: #REF!
Name System: #REF!
Name System: #REF!
Name Tag: #REF!
Name Tag: #REF!
Name Tag: #REF!
Name Test_Discipline: Disciplines
Name Test_Discipline: Disciplines
Name Test_Discipline: Disciplines

Sheet Main Dashboard (1)
B2: PCS-Close Out Monthly Report
B8: Project Name: | E8: Budget:
B9: Employer: | E9: Commencement date:
B10: Design consultant | E10: Contract completion date:
B11: Supervision consultant | E11: Modified / forecasted completion date :
B12: Contractor: | E12: Total contractual project duration:
B13: Project Manager
B14: Date:
E15: Overall Close Out Report
E29: Complied Criteria on Close Out Monthly Report
E30: Actual Construction Status as of August-16
B31: No | C31: Criteria | D31: Weight | E31: Actual achievement | F31: Remarks
B32: 1 | C32: O&M manuals | D32: 0.05 | E32: ='Detailed Dashboard(2)'!E16 -> 0.03 | F32: progressing properly
B33: 2 | C33: Testing & Commissioning | D33: 0.05 | E33: ='Detailed Dashboard(2)'!E23 -> 0.02 | F33: End of project f inal report to be attached within the close out report
B34: 3 | C34: Training | D34: ='Detailed Dashboard(2)'!Q11 -> 0.05 | E34: 0.05 | F34: PM to confirm no training sessions required on the contract
B35: 4 | C35: Authorities approval | D35: 0.15 | E35: ='Detailed Dashboard(2)'!E45 -> 0
B36: 5 | C36: Asset register | D36: ='Detailed Dashboard(2)'!Q13 -> 0.05 | E36: 0.03 | F36: progressing properly
B37: 6 | C37: As built drawings | D37: 0.1 | E37: ='Detailed Dashboard(2)'!R14 -> 0.01 | F37: progressing ,Log approved
B38: 7 | C38: Master Key & Access Cards | D38: ='Detailed Dashboard(2)'!Q15 -> 0.05 | E38: ='Detailed Dashboard(2)'!E59 -> 0.01 | F38: progressing ,Log approved
B39: 8 | C39: Spare parts/special tools | D39: ='Detailed Dashboard(2)'!Q16 -> 0.05 | E39: ='Detailed Dashboard(2)'!E71 -> 0.01 | F39: progressing ,Log approved
B40: 9 | C40: Updated Snags List | D40: 0.05 | E40: ='Detailed Dashboard(2)'!E86 -> 0 | F40: On the due time will be progress
B41: 10 | C41: QA/QC Report | D41: 0.1 | E41: 0.07 | F41: Musanada approved QA/QC Template to be used
B42: 11 | C42: HSE report | D42: 0.1 | E42: ='Detailed Dashboard(2)'!E94 -> 0.07 | F42: Musanada approved HSE Template to be used
B43: 12 | C43: Warranties | D43: ='Detailed Dashboard(2)'!Q20 -> 0.05 | E43: ='Detailed Dashboard(2)'!E101 -> 0.005 | F43: progressing ,Log approved
B44: 13 | C44: lesson learned | D44: ='Detailed Dashboard(2)'!Q21 -> 0.05 | E44: 0.05 | F44: All captured
B45: 14 | C45: Taking Over Certificate | D45: ='Detailed Dashboard(2)'!Q22 -> 0.05 | E45: ='Detailed Dashboard(2)'!R22 -> 0 | F45: ON the due date will to update PCS-Close out unit
B46: 15 | C46: Close Out Report | D46: 0.05 | E46: 0.027 | F46: Prepration going on

Sheet Detailed Dashboard(2)
A2: PCS-Close Out Monthly Report Actual Construction Status as of
P6: s.no
P8: S.no | Q8: Assigned Weight | R8: Actuals To Date | S8: Balance To Complete
A9: 1- O&M Manuals | C9: Assigned Weight | E9: 0.05 | P9: 1 | Q9: =E9 -> 0.05 | R9: 0.03 | S9: =Q9-R9 -> 0.02
B10: Weight | C10: Quantity | D10: Achievements | E10: Status | P10: 2 | Q10: =E17 -> 0.1 | R10: 0.02 | S10: =Q10-R10 -> 0.08
A11: 1.1 -Total numbers of O &M manuals required as per building systems component , | P11: 3 | Q11: =E24 -> 0.05 | R11: 0.005 | S11: 0.045
A12: defined and agreed between contractor and consultant , fixed in a log sheet for tracking | B12: 0.2 | C12: 5 | D12: 1 | E12: =D12*B12*E9 -> 0.01 | P12: 4 | Q12: 0.05 | R12: =D45 -> 0 | S12: =Q12-R12 -> 0.05
A13: 1.2- Total O & M numbers approved by Consultant & confirmed by PM | B13: 0.4 | C13: 5 | D13: 1 | E13: =D13*B13*E9 -> 0.02 | P13: 5 | Q13: 0.05 | R13: 0.01 | S13: =Q13-R13 -> 0.04
A14: 1.3- Total O & M numbers Reviewed & accepted by FM/client representative/end user | B14: 0.3 | C14: 0 | D14: 0 | E14: 0 | P14: 6 | Q14: =E53 -> 0.05 | R14: 0.01 | S14: =Q14-R14 -> 0.04
A15: 1.4- Total complete quantity consisting all twenty sections delivered to the site | B15: 0.1 | C15: 0 | D15: 0 | E15: 0 | P15: 7 | Q15: =E60 -> 0.05 | R15: 0.01 | S15: 0.04
A16: O&M Manuals Actual % To Date | E16: 0.03 | P16: 8 | Q16: 0.05 | R16: 0.005 | S16: 0.045
A17: 2- Testing & Commissioning (T&C) | C17: Assigned Weight | E17: 0.1 | P17: 9 | Q17: 0.05 | R17: =D86 -> 0 | S17: =Q17-R17 -> 0.05
B18: Weight | C18: Quantity | D18: Achievements | E18: Status | P18: 10 | Q18: =E87 -> 0.1 | R18: 0.05 | S18: =Q18-R18 -> 0.05
A19: 2.1 -Total number of systems T&C test must be carried out as per building system components wise , the same to be prepared as per the attached sheet bearing consultant, contractor and third-party stamps , the same to be updated every week | B19: 0.2 | C19: 4216 | D19: 1 | E19: =SUM(D19*B19)*$E$17 -> 0.02 | P19: 11 | Q19: 0.1 | R19: 0.05 | S19: =Q19-R19 -> 0.05
A20: 2.2.Total number of passed test stage commissioning (ATP3) as stand alone | B20: 0.7 | C20: 0 | D20: 0 | E20: 0 | P20: 12 | Q20: 0.05 | R20: 0.005 | S20: =Q20-R20 -> 0.045
A21: 2.3- Total number of passed test stage integration with BMS (ATP4) | B21: 0 | C21: 0 | D21: 0 | E21: 0 | P21: 13 | Q21: 0.05 | R21: 0.03 | S21: =Q21-R21 -> 0.02
A22: 2.4- Final T&C report issued and approved from all parties (contractor, consultant, Third party PM and UPC) | B22: 0.1 | C22: 0 | D22: 0 | E22: 0 | P22: 14 | Q22: 0.05 | R22: =D111 -> 0 | S22: =Q22-R22 -> 0.05
A23: T&C Actual % To Date | E23: 0.02 | P23: 15 | Q23: 0.05 | R23: 0.027 | S23: 0.013
A24: 3- Training | C24: Assigned Weight | E24: 0.05 | P24: Grand Total | Q24: 1 | R24: 0.383 | S24: 0.617
B25: Weight | C25: Quantity | D25: Achievements | E25: Status
A26: 3.1 -Total number of systems required training defined by contract to be prepared in the attached flow sheet with schedule plan dates | B26: 0.1 | C26: 10 | D26: 1 | E26: =D26*B26*E24 -> 0.005
A27: 3.2 -Consultant and PM confirmed on achievement training by contractor/supplier to FM and client representatives | B27: 0.4 | C27: 0 | D27: 0 | E27: 0
A28: 3.3 -Approval on achieved training by FM and client | B28: 0.5 | C28: 0 | D28: 0 | E28: 0
A29: Training Actual % To Date | E29: 0.005
A30: 4- Authorities Approvals | C30: Assigned Weight | E30: 0.15
B31: Weight | C31: Quantity | D31: Achievements | E31: Status
A32: 4.1 Abu Dhabi Al Ain Municipality (Building complstion certificate) | B32: 0.1 | C32: 1 | D32: 0 | E32: 0
A33: 4.2 Abu Dhabi Sewerage Service Company (ADSSC) | B33: 0.1 | C33: 1 | D33: 0 | E33: 0
A34: 4.3 AbuDhabi/ Al Ain Distribution Company Power ( ADDC & AADC - Power) | B34: 0.1 | C34: 1 | D34: 0 | E34: 0
A35: 4.4 AbuDhabi/ Al Ain Distribution Company Water (AADC - Water) | B35: 0.1 | C35: 1 | D35: 0 | E35: 0
A36: 4.5 Telecom authority / Etisalat | B36: 0.1 | C36: 1 | D36: 0 | E36: 0
A37: 4.6 AbuDhab/Al Ain City Municipality(Storm Water Network) | B37: 0.05 | C37: 1 | D37: 0 | E37: 0 | R37: Not to fill/Modify any thing on first two Sheet- 1 & 2
A38: 4.7 AbuDhabi /Al Ain City Municipality(Irrigation Network) | B38: 0.05 | C38: 1 | D38: 0 | E38: 0
A39: 4.8 AbuDhabi / Al Ain City Municipality(PRFD) | B39: 0.05 | C39: 1 | D39: 0 | E39: 0
A40: 4.9 AbuDhabi /Al Ain City Municipality(Street Light Network) | B40: 0.05 | C40: 1 | D40: 0 | E40: 0
A41: 4.10 AbuDhabi /Al Ain City Municipality(Road Works) | B41: 0.05 | C41: 1 | D41: 0 | E41: 0
A42: 4.11 Civil defence for fire hydrant net work | B42: 0.1 | C42: 1 | D42: 0 | E42: 0
A43: 4.12UPC - Estidama /villa /community | B43: 0.1 | C43: 1 | D43: 0 | E43: 0
A44: 4.13 Department of Transport(Traffic Signal) | B44: 0.05 | C44: 1 | D44: 0 | E44: 0
A45: Authorities Approvals Actual % To Date | E45: =SUM(E32:E44) -> 0
A46: 5- Assets Register | C46: Assigned Weight | E46: 0.05
B47: Weight | C47: Quantity | D47: Achievements | E47: Status | R47: Other attached excel sheets will be filled witth the information.sheet 1 & 2 for referance and information only.
A48: 5.1 -Total No's of assets systems must be registered base on building component break down list prepared by contractor as per attached Musanda format or/ client format | B48: 0.2 | C48: 29646 | D48: 1 | E48: =SUM(D48*B48)*$E$46 -> 0.01
A49: 5.2- Total No's prepared Building component breakdown list, as per Musanada or client format reviewed and approved by consultant and PM | B49: 0.4 | C49: 29646 | D49: 1 | E49: =D49*B49*E46 -> 0.02
A50: 5.3 -Total No's reviewed accepted by FM or client (Asset manager) | B50: 0.4 | C50: 0 | D50: 0 | E50: 0
A52: Asset Register Actual % To Date | E52: =SUM(E48:E50) -> 0.03
A53: 6- As Built Drawings | C53: Assigned Weight | E53: 0.05
B54: Weight | C54: Quantity | D54: Achievements | E54: Status
A55: 6.1 -Total quantity of as built drawings (agreed by PM/consultant / contractor) as per building systems components wise , to be followed on tracker sheet | B55: 0.2 | C55: 564 | D55: 1 | E55: 0.01
A56: 6.2 Total quantity of as built drawings approved by consultant and confirmed by PM | B56: 0.4 | C56: 0 | E56: 0
A57: 6.3- Total quantity of as built drawings reviewed & and accepted by FM or client representative | B57: 0.3 | C57: 0 | D57: 0 | E57: 0
A58: 6.4- Total quantity of as built soft and hard copy delivered and distributed | B58: 0.1 | C58: 0 | D58: 0 | E58: 0
A59: As Built Drawings Actual % To Date | E59: =SUM(E55:E58) -> 0.01
A60: 7- Master Keys & Access Cards | C60: Assigned Weight | E60: 0.05
B61: Weight | C61: Quantity | D61: Achievements | E61: Status
A62: 7.1-Total number of keys must be submitted by Contractor | B62: 0.2 | C62: 3566 | D62: 1 | E62: =D62*B62*E60 -> 0.01
A63: Keys Per room (doors). | C63: 0
A64: Master Keys Per Zone - Sub Master Key (SMK)
A65: Main Master Keys - Grand Master Key (GMK)
A66: 7.2- Approved by consultant & Reviewed by PM and confirmed by FM | B66: 0.2 | C66: 0 | D66: 0 | E66: 0
A67: 7.3 - PM submitted to client security representatives | B67: 0.2 | C67: 0 | D67: 0 | E67: 0
A68: 7.4 -Total number of access cards must be submitted by Contractor
A69: 7.5 - Approved by consultant & Reviewed by PM and confirmed by FM | B69: 0.2 | C69: 0 | D69: 0 | E69: 0
A70: 7.6 -PM submitted to client security representatives | B70: 0.2 | C70: 0 | D70: 0 | E70: 0
A71: Master Keys & Access Cards Actual % To Date | E71: =SUM(E62:E70) -> 0.01
A72: 8- Spare Parts / Special Tools | C72: Assigned Weight | E72: 0.05
B73: Weight | C73: Quantity | D73: Achievements | E73: Status | V73: 0
A74: 8.1 -Total number of spare parts/special tools to be submitted by main contractor as per the contractual obligation | B74: 0.1 | C74: 11 | D74: 1 | E74: =D74*B74*E72 -> 0.005 | V74: 1
A75: 8.2 Approved by consultant | B75: 0.2 | C75: 0 | D75: 0 | E75: 0
A76: 8.3- Acceptance and confirmed by PM | B76: 0.2 | C76: 0 | D76: 0 | E76: 0
A77: 8.4- FM or client accepted to receive and deliver | B77: 0.2 | C77: 0 | D77: 0 | E77: 0
A78: 8.5 -PM confirmed Spare Parts / Special tools delivered to site | B78: 0.3 | C78: 0 | D78: 0 | E78: 0
A79: Spare Parts / Special Tools Actual % To date | E79: =SUM(E74:E78) -> 0.005
A80: 9- Updated Snag List | C80: Assigned Weight | E80: 0.05
B81: Weight | C81: Quantity | D81: Achievements | E81: Status
A82: 9.1 -Total lists of snags for all discipline's to be prepared by contractor and agreed with consultant and PM | B82: 0.1 | C82: 0 | D82: 0 | E82: 0
A83: 9.2 Consultant approval for the list of snags and confirmed by PM | B83: 0.2 | C83: 0 | D83: 0 | E83: 0
A84: 9.3- Final lists of snags reviewed by FM/client/client representative | B84: 0.3 | C84: 0 | D84: 0 | E84: 0
A85: 9.4- BCM and FM Divisions agreed on way forward plan and responsibilities to deliver snags | B85: 0.4 | C85: 0 | D85: 0 | E85: 0
A86: Updated Snag List Actual % To Date | E86: =SUM(E82:E85) -> 0
A87: 10- Quality Assurance Report | C87: Assigned Weight | E87: 0.1
B88: Weight | C88: Report | D88: Achievements | E88: Status
A89: 10.1-QA/QC Monthly reports updates prepared and approved by consultant ,PM | B89: 1 | C89: 1 | D89: 0.5 | E89: =(D89*B89*E87) -> 0.05 | S89: 5
A90: Quality Assurance Report Actual % To Date | E90: =SUM(E89) -> 0.05
A91: 11- HSE Report | C91: Assigned Weight | E91: 0.1
B92: Weight | C92: Report | D92: Achievements | E92: Status
A93: 11.1-HSE Monthly reports updates prepared and approved by consultant ,PM | B93: 1 | C93: 1 | D93: 0.7 | E93: =D93*B93*E91 -> 0.07
A94: HSE Report Actual % To Date | E94: =SUM(E93) -> 0.07
A95: 12- Warranties | C95: Assigned Weight | E95: 0.05
B96: Weight | C96: Quantity | D96: Achievements | E96: Status
A97: 12.1-Total number of warranties must be submitted by main contractor as per building component system wise fixed in a logsheet for tracking | B97: 0.1 | C97: 22 | D97: 1 | E97: =D97*B97*E95 -> 0.005
A98: 12.2- Total number of warranties (draft) approved by consultant &confirmed by PM | B98: 0.5 | C98: 22 | D98: 0 | E98: 0
A99: 12.3 -Total number of warranties(draft) reviewed and accepted by FM | B99: 0.2 | C99: 22 | D99: 0 | E99: 0
A100: 12.4 -PM & FM confirmation on the receipt of total number of original warranties | B100: 0.2 | C100: 22 | D100: 0 | E100: =(D100*C99*B100)*$E$95 -> 0
A101: Warranties Actual % To Date | E101: 0.005
A102: 13- Lesson Learned | C102: Assigned Weight | E102: 0.05
B103: Weight | C103: Report | D103: Achievements | E103: Status
A104: 13.1- Lesson learned shared, gathered and captured by PM on Musanda attached format | B104: 0.5 | C104: 1 | D104: 1 | E104: =D104*B104*E102 -> 0.025
A105: 13.2- PM Submit the collected lesson learned to the design section | B105: 0.5 | C105: 1 | D105: 0 | E105: 0.025
A106: Lesson Learned Actual % To Date | E106: =SUM(E104:E105) -> 0.05
...

Sheet Flow sheet (16) close out repor
B2: Flow sheet No(16) for close out report
B7: Project Closeout Report | I7: No | J7: Appendixes | K7: Weight | L7: Status
B8: No | C8: Contents | D8: Weight | E8: Status | I8: 1 | J8: Commercial report | K8: 0.03
B9: 1 | C9: Brief Description of Projects | D9: 0.02 | I9: 2 | J9: Remaining works/defects | K9: 0.02
B10: 2 | C10: Key Milestone Dates for Projects | D10: 0.03 | I10: 3 | J10: List of as-built drawings & soft copy | K10: 0.05
B11: 3 | C11: Project Cost Details | D11: 0.04 | I11: 4 | J11: List of O&M manuals & soft copy | K11: 0.05
B12: 4 | C12: Client | D12: 0.01 | I12: 5 | J12: Testing & commissioning records | K12: 0.05
B13: 5 | C13: Employer | D13: 0.01 | I13: 6 | J13: List of spare parts/materials | K13: 0.05 | U13: :
B14: 6 | C14: Project Management Consultant | D14: 0.01 | I14: 7 | J14: Original warrantees & guaranties | K14: 0.03
B15: 7 | C15: Consultant | D15: 0.01 | I15: 8 | J15: Original statutory permits & NOCs | K15: 0.05
B16: 8 | C16: Contractor | D16: 0.01 | I16: 9 | J16: List of keys & access cards | K16: 0.02
B17: 9 | C17: Design Review/Lessons Learned & Recommendations | D17: 0.2 | I17: 10 | J17: List of training | K17: 0.03
B18: 10 | C18: Other Matters | D18: 0.01 | I18: 11 | J18: Assets register | K18: 0.05
B19: 11 | C19: Photographs | D19: 0.05 | I19: 12 | J19: Health & safety file | K19: 0.02
B20: Total | D20: =SUM(D9:D19) -> 0.4 | I20: 13 | J20: As-built specifications | K20: 0.05
I21: 14 | J21: Sustainability targets | K21: 0.05
I22: 15 | J22: Risk registry | K22: 0.02
I23: 16 | J23: Quality control records | K23: 0.03
I24: Total | K24: =SUM(K8:K23) -> 0.6
C27: Musanada Template for preparing project close out report…to be used
